adjdatatools/__init__.py
adjdatatools/preprocessing.py
adjdatatools-0.4.0.dist-info/LICENSE
adjdatatools-0.4.0.dist-info/METADATA
adjdatatools-0.4.0.dist-info/WHEEL
adjdatatools-0.4.0.dist-info/top_level.txt
adjdatatools-0.4.0.dist-info/RECORD
