Metadata-Version: 2.1
Name: adjdatatools
Version: 0.4.0
Summary: This library contains adjusted tools for data preprocessing and working with mixed data types.
Home-page: https://github.com/newchronik/adjdatatools
Author: Anton Kvasnitsa
Author-email: anton.kvasnitsa@gmail.com
License: MIT
Keywords: data preprocessing scaler
Platform: UNKNOWN
Requires-Dist: numpy
Requires-Dist: pandas (>=0.20.0)
